ses_mailer/__init__.py
SES_Mailer_3-0.15.6.dist-info/LICENSE
SES_Mailer_3-0.15.6.dist-info/METADATA
SES_Mailer_3-0.15.6.dist-info/WHEEL
SES_Mailer_3-0.15.6.dist-info/top_level.txt
SES_Mailer_3-0.15.6.dist-info/RECORD
