Metadata-Version: 2.1
Name: SES-Mailer-3
Version: 0.15.6
Summary: A simple module to send email via AWS SES
Home-page: https://github.com/tclark/ses-mailer
Author: Tom Clark
Author-email: tclark@requisitesystems.com
License: UNKNOWN
Project-URL: Bug Tracker, https://github.com/tclark/ses-mailer/issues
Platform: UNKNOWN
Classifier: Intended Audience :: Developers
Classifier: Topic :: Software Development :: Libraries :: Python Modules
Classifier: Programming Language :: Python :: 2
Classifier: Programming Language :: Python :: 2.7
Classifier: Programming Language :: Python :: 3
Classifier: Programming Language :: Python :: 3.7
Classifier: Programming Language :: Python :: 3.8
Classifier: Programming Language :: Python :: 3.9
Classifier: License :: OSI Approved :: MIT License
Classifier: Operating System :: OS Independent
Requires-Python: >=2.7
License-File: LICENSE
Requires-Dist: jinja2
Requires-Dist: boto3
